ai6lib/__init__.py
ai6lib/eprint.py
ai6lib-0.0.1.dist-info/METADATA
ai6lib-0.0.1.dist-info/WHEEL
ai6lib-0.0.1.dist-info/top_level.txt
ai6lib-0.0.1.dist-info/RECORD
