Metadata-Version: 2.4
Name: ai6lib
Version: 0.0.1
Summary: For demonstrating library creation
Home-page: https://github.com/pypa/advisory-database
Author: Mindaugas Bernatavicius
Author-email: testtest2@gmail.com
Classifier: Programming Language :: Python :: 3
Classifier: License :: OSI Approved :: MIT License
Classifier: Operating System :: OS Independent
Requires-Python: >=3.8
